memokit/__init__.py
memokit/pool.py
memokit/space.py
memokit/utils.py
memokit/db/__init__.py
memokit/db/pickle.py
memokit-0.0.2.dist-info/METADATA
memokit-0.0.2.dist-info/WHEEL
memokit-0.0.2.dist-info/top_level.txt
memokit-0.0.2.dist-info/RECORD
