Metadata-Version: 2.4
Name: memokit
Version: 0.0.2
Summary: ai memory kit
Author-email: rickey <hello_rickey@163.com>
License-Expression: MIT
Project-URL: Homepage, https://github.com/AmeNetwork/memokit
Project-URL: Bug Tracker, https://github.com/AmeNetwork/memokit/issues
Requires-Python: >=3.13.2
Requires-Dist: openai>=1.63.2
Requires-Dist: python-dotenv>=1.0.1
Requires-Dist: pickleDB>=1.3.2
